{
  "timestamp": "20260628_095739",
  "title": "Scalability n_obj=50 n_comp=150",
  "mode": "big_m",
  "inputs": {
    "num_objectives": 50,
    "objectives": [
      "o_1",
      "o_2",
      "o_3",
      "o_4",
      "o_5",
      "o_6",
      "o_7",
      "o_8",
      "o_9",
      "o_10",
      "o_11",
      "o_12",
      "o_13",
      "o_14",
      "o_15",
      "o_16",
      "o_17",
      "o_18",
      "o_19",
      "o_20",
      "o_21",
      "o_22",
      "o_23",
      "o_24",
      "o_25",
      "o_26",
      "o_27",
      "o_28",
      "o_29",
      "o_30",
      "o_31",
      "o_32",
      "o_33",
      "o_34",
      "o_35",
      "o_36",
      "o_37",
      "o_38",
      "o_39",
      "o_40",
      "o_41",
      "o_42",
      "o_43",
      "o_44",
      "o_45",
      "o_46",
      "o_47",
      "o_48",
      "o_49",
      "o_50"
    ],
    "num_plans": 300,
    "num_comparisons": 150
  },
  "model_stats": {
    "num_variables": 767000,
    "num_constraints": 3102441
  },
  "result": {
    "status": "OPTIMAL",
    "feasible": true,
    "optimal": true,
    "objective_value": 49.0,
    "preorder_size": 49,
    "preorder_edges": [
      [
        "o_2",
        "o_1"
      ],
      [
        "o_3",
        "o_1"
      ],
      [
        "o_4",
        "o_1"
      ],
      [
        "o_5",
        "o_1"
      ],
      [
        "o_6",
        "o_1"
      ],
      [
        "o_7",
        "o_1"
      ],
      [
        "o_8",
        "o_1"
      ],
      [
        "o_9",
        "o_1"
      ],
      [
        "o_10",
        "o_1"
      ],
      [
        "o_11",
        "o_1"
      ],
      [
        "o_12",
        "o_1"
      ],
      [
        "o_13",
        "o_1"
      ],
      [
        "o_14",
        "o_1"
      ],
      [
        "o_15",
        "o_1"
      ],
      [
        "o_16",
        "o_1"
      ],
      [
        "o_17",
        "o_1"
      ],
      [
        "o_18",
        "o_1"
      ],
      [
        "o_19",
        "o_1"
      ],
      [
        "o_20",
        "o_1"
      ],
      [
        "o_21",
        "o_1"
      ],
      [
        "o_22",
        "o_1"
      ],
      [
        "o_23",
        "o_1"
      ],
      [
        "o_24",
        "o_1"
      ],
      [
        "o_25",
        "o_1"
      ],
      [
        "o_26",
        "o_1"
      ],
      [
        "o_27",
        "o_1"
      ],
      [
        "o_28",
        "o_1"
      ],
      [
        "o_29",
        "o_1"
      ],
      [
        "o_30",
        "o_1"
      ],
      [
        "o_31",
        "o_1"
      ],
      [
        "o_32",
        "o_1"
      ],
      [
        "o_33",
        "o_1"
      ],
      [
        "o_34",
        "o_1"
      ],
      [
        "o_35",
        "o_1"
      ],
      [
        "o_36",
        "o_1"
      ],
      [
        "o_37",
        "o_1"
      ],
      [
        "o_38",
        "o_1"
      ],
      [
        "o_39",
        "o_1"
      ],
      [
        "o_40",
        "o_1"
      ],
      [
        "o_41",
        "o_1"
      ],
      [
        "o_42",
        "o_1"
      ],
      [
        "o_43",
        "o_1"
      ],
      [
        "o_44",
        "o_1"
      ],
      [
        "o_45",
        "o_1"
      ],
      [
        "o_46",
        "o_1"
      ],
      [
        "o_47",
        "o_1"
      ],
      [
        "o_48",
        "o_1"
      ],
      [
        "o_49",
        "o_1"
      ],
      [
        "o_50",
        "o_1"
      ]
    ]
  },
  "verification": {
    "verified": true,
    "preorder_size": 49,
    "num_comparisons_checked": 150,
    "violations": [],
    "num_violations": 0
  },
  "timing": {
    "construction_time_sec": 31.597189749999984,
    "solver_time_sec": 23.242058458000002,
    "total_time_sec": 54.841375459000005,
    "detailed_intervals": {
      "variable_creation": 1.0905047499999796,
      "transitivity_constraints": 1.0264655000000005,
      "y_computation_constraints": 28.560256708000026,
      "comparison_constraints": 0.2910355419999746,
      "constraint_addition": 29.877765458,
      "total_build": 31.596459832999983,
      "solver_time": 23.21970225000001
    }
  }
}